[
  {
    "cmd": [],
    "name": "ensure_gitiles"
  },
  {
    "cmd": [
      "cipd",
      "ensure",
      "-root",
      "[START_DIR]/cipd/gitiles",
      "-ensure-file",
      "infra/tools/luci/gitiles/linux-amd64 latest",
      "-json-output",
      "/path/to/tmp/json"
    ],
    "infra_step": true,
    "name": "ensure_gitiles.ensure_installed",
    "~followup_annotations": [
      "@@@STEP_NEST_LEVEL@1@@@",
      "@@@STEP_LOG_LINE@json.output@{@@@",
      "@@@STEP_LOG_LINE@json.output@  \"result\": [@@@",
      "@@@STEP_LOG_LINE@json.output@    {@@@",
      "@@@STEP_LOG_LINE@json.output@      \"instance_id\": \"resolved-instance_id-of-latest----------\", @@@",
      "@@@STEP_LOG_LINE@json.output@      \"package\": \"infra/tools/luci/gitiles/linux-amd64\"@@@",
      "@@@STEP_LOG_LINE@json.output@    }@@@",
      "@@@STEP_LOG_LINE@json.output@  ]@@@",
      "@@@STEP_LOG_LINE@json.output@}@@@",
      "@@@STEP_LOG_END@json.output@@@"
    ]
  },
  {
    "cmd": [],
    "name": "ensure_goma"
  },
  {
    "cmd": [
      "cipd",
      "ensure",
      "-root",
      "[CACHE]/goma/client",
      "-ensure-file",
      "infra_internal/goma/client/${platform} release",
      "-json-output",
      "/path/to/tmp/json"
    ],
    "infra_step": true,
    "name": "ensure_goma.ensure_installed",
    "~followup_annotations": [
      "@@@STEP_NEST_LEVEL@1@@@",
      "@@@STEP_LOG_LINE@json.output@{@@@",
      "@@@STEP_LOG_LINE@json.output@  \"result\": {@@@",
      "@@@STEP_LOG_LINE@json.output@    \"\": [@@@",
      "@@@STEP_LOG_LINE@json.output@      {@@@",
      "@@@STEP_LOG_LINE@json.output@        \"instance_id\": \"resolved-instance_id-of-release---------\", @@@",
      "@@@STEP_LOG_LINE@json.output@        \"package\": \"infra_internal/goma/client/resolved-platform\"@@@",
      "@@@STEP_LOG_LINE@json.output@      }@@@",
      "@@@STEP_LOG_LINE@json.output@    ]@@@",
      "@@@STEP_LOG_LINE@json.output@  }@@@",
      "@@@STEP_LOG_LINE@json.output@}@@@",
      "@@@STEP_LOG_END@json.output@@@"
    ]
  },
  {
    "cmd": [],
    "name": "ensure_gsutil"
  },
  {
    "cmd": [
      "cipd",
      "ensure",
      "-root",
      "[START_DIR]/cipd/gsutil",
      "-ensure-file",
      "infra/tools/gsutil latest",
      "-json-output",
      "/path/to/tmp/json"
    ],
    "infra_step": true,
    "name": "ensure_gsutil.ensure_installed",
    "~followup_annotations": [
      "@@@STEP_NEST_LEVEL@1@@@",
      "@@@STEP_LOG_LINE@json.output@{@@@",
      "@@@STEP_LOG_LINE@json.output@  \"result\": {@@@",
      "@@@STEP_LOG_LINE@json.output@    \"\": [@@@",
      "@@@STEP_LOG_LINE@json.output@      {@@@",
      "@@@STEP_LOG_LINE@json.output@        \"instance_id\": \"resolved-instance_id-of-latest----------\", @@@",
      "@@@STEP_LOG_LINE@json.output@        \"package\": \"infra/tools/gsutil\"@@@",
      "@@@STEP_LOG_LINE@json.output@      }@@@",
      "@@@STEP_LOG_LINE@json.output@    ]@@@",
      "@@@STEP_LOG_LINE@json.output@  }@@@",
      "@@@STEP_LOG_LINE@json.output@}@@@",
      "@@@STEP_LOG_END@json.output@@@"
    ]
  },
  {
    "cmd": [
      "[START_DIR]/cipd/gitiles/gitiles",
      "refs",
      "-json-output",
      "/path/to/tmp/json",
      "https://gnu.googlesource.com/binutils-gdb",
      "refs"
    ],
    "name": "binutils refs",
    "~followup_annotations": [
      "@@@STEP_LOG_LINE@json.output@{@@@",
      "@@@STEP_LOG_LINE@json.output@  \"refs/heads/binutils-2_31-branch\": \"3d861fdb826c2f5cf270dd5f585d0e6057e1bf4f\"@@@",
      "@@@STEP_LOG_LINE@json.output@}@@@",
      "@@@STEP_LOG_END@json.output@@@"
    ]
  },
  {
    "cmd": [
      "[START_DIR]/cipd/gitiles/gitiles",
      "refs",
      "-json-output",
      "/path/to/tmp/json",
      "https://gnu.googlesource.com/gcc",
      "refs"
    ],
    "name": "gcc refs",
    "~followup_annotations": [
      "@@@STEP_LOG_LINE@json.output@{@@@",
      "@@@STEP_LOG_LINE@json.output@  \"refs/tags/gcc-8_2_0-release\": \"4b5e15daff8b54440e3fda451c318ad31e532fab\"@@@",
      "@@@STEP_LOG_LINE@json.output@}@@@",
      "@@@STEP_LOG_END@json.output@@@"
    ]
  },
  {
    "cmd": [
      "cipd",
      "search",
      "fuchsia/gcc/linux-amd64",
      "-tag",
      "git_revision:4b5e15daff8b54440e3fda451c318ad31e532fab,3d861fdb826c2f5cf270dd5f585d0e6057e1bf4f",
      "-json-output",
      "/path/to/tmp/json"
    ],
    "name": "cipd search fuchsia/gcc/linux-amd64 git_revision:4b5e15daff8b54440e3fda451c318ad31e532fab,3d861fdb826c2f5cf270dd5f585d0e6057e1bf4f",
    "~followup_annotations": [
      "@@@STEP_LOG_LINE@json.output@{@@@",
      "@@@STEP_LOG_LINE@json.output@  \"result\": []@@@",
      "@@@STEP_LOG_LINE@json.output@}@@@",
      "@@@STEP_LOG_END@json.output@@@"
    ]
  },
  {
    "cmd": [],
    "name": "ensure_packages"
  },
  {
    "cmd": [
      "cipd",
      "ensure",
      "-root",
      "[START_DIR]/cipd",
      "-ensure-file",
      "fuchsia/clang/${platform} goma\nfuchsia/sysroot/${platform} latest",
      "-json-output",
      "/path/to/tmp/json"
    ],
    "infra_step": true,
    "name": "ensure_packages.ensure_installed",
    "~followup_annotations": [
      "@@@STEP_NEST_LEVEL@1@@@",
      "@@@STEP_LOG_LINE@json.output@{@@@",
      "@@@STEP_LOG_LINE@json.output@  \"result\": [@@@",
      "@@@STEP_LOG_LINE@json.output@    {@@@",
      "@@@STEP_LOG_LINE@json.output@      \"instance_id\": \"resolved-instance_id-of-goma------------\", @@@",
      "@@@STEP_LOG_LINE@json.output@      \"package\": \"fuchsia/clang/${platform}\"@@@",
      "@@@STEP_LOG_LINE@json.output@    }, @@@",
      "@@@STEP_LOG_LINE@json.output@    {@@@",
      "@@@STEP_LOG_LINE@json.output@      \"instance_id\": \"resolved-instance_id-of-latest----------\", @@@",
      "@@@STEP_LOG_LINE@json.output@      \"package\": \"fuchsia/sysroot/${platform}\"@@@",
      "@@@STEP_LOG_LINE@json.output@    }@@@",
      "@@@STEP_LOG_LINE@json.output@  ]@@@",
      "@@@STEP_LOG_LINE@json.output@}@@@",
      "@@@STEP_LOG_END@json.output@@@"
    ]
  },
  {
    "cmd": [
      "cipd",
      "describe",
      "fuchsia/gcc/linux-amd64",
      "-version",
      "latest",
      "-json-output",
      "/path/to/tmp/json"
    ],
    "name": "cipd describe fuchsia/gcc/linux-amd64",
    "~followup_annotations": [
      "@@@STEP_LOG_LINE@json.output@{@@@",
      "@@@STEP_LOG_LINE@json.output@  \"result\": {@@@",
      "@@@STEP_LOG_LINE@json.output@    \"pin\": {@@@",
      "@@@STEP_LOG_LINE@json.output@      \"instance_id\": \"resolved-instance_id-of-latest----------\", @@@",
      "@@@STEP_LOG_LINE@json.output@      \"package\": \"fuchsia/gcc/linux-amd64\"@@@",
      "@@@STEP_LOG_LINE@json.output@    }, @@@",
      "@@@STEP_LOG_LINE@json.output@    \"refs\": [@@@",
      "@@@STEP_LOG_LINE@json.output@      {@@@",
      "@@@STEP_LOG_LINE@json.output@        \"modified_by\": \"user:44-blablbla@developer.gserviceaccount.com\", @@@",
      "@@@STEP_LOG_LINE@json.output@        \"modified_ts\": 1446574210, @@@",
      "@@@STEP_LOG_LINE@json.output@        \"ref\": \"latest\"@@@",
      "@@@STEP_LOG_LINE@json.output@      }@@@",
      "@@@STEP_LOG_LINE@json.output@    ], @@@",
      "@@@STEP_LOG_LINE@json.output@    \"registered_by\": \"user:44-blablbla@developer.gserviceaccount.com\", @@@",
      "@@@STEP_LOG_LINE@json.output@    \"registered_ts\": 1446574210, @@@",
      "@@@STEP_LOG_LINE@json.output@    \"tags\": [@@@",
      "@@@STEP_LOG_LINE@json.output@      {@@@",
      "@@@STEP_LOG_LINE@json.output@        \"registered_by\": \"user:44-blablbla@developer.gserviceaccount.com\", @@@",
      "@@@STEP_LOG_LINE@json.output@        \"registered_ts\": 1446574210, @@@",
      "@@@STEP_LOG_LINE@json.output@        \"tag\": \"git_revision:b824b5a2484202f6eabbe118b1cf7682ce77b76e,5898623efb820fc56123da2e316756a9a32cb59b\"@@@",
      "@@@STEP_LOG_LINE@json.output@      }@@@",
      "@@@STEP_LOG_LINE@json.output@    ]@@@",
      "@@@STEP_LOG_LINE@json.output@  }@@@",
      "@@@STEP_LOG_LINE@json.output@}@@@",
      "@@@STEP_LOG_END@json.output@@@"
    ]
  },
  {
    "cmd": [
      "python",
      "-u",
      "RECIPE_MODULE[recipe_engine::file]/resources/fileutil.py",
      "--json-output",
      "/path/to/tmp/json",
      "ensure-directory",
      "--mode",
      "0777",
      "[START_DIR]/binutils-gdb"
    ],
    "infra_step": true,
    "name": "makedirs"
  },
  {
    "cmd": [
      "git",
      "init"
    ],
    "cwd": "[START_DIR]/binutils-gdb",
    "infra_step": true,
    "name": "git init"
  },
  {
    "cmd": [
      "git",
      "remote",
      "add",
      "origin",
      "https://gnu.googlesource.com/binutils-gdb"
    ],
    "cwd": "[START_DIR]/binutils-gdb",
    "infra_step": true,
    "name": "git remote"
  },
  {
    "cmd": [
      "git",
      "fetch",
      "origin"
    ],
    "cwd": "[START_DIR]/binutils-gdb",
    "infra_step": true,
    "name": "git fetch"
  },
  {
    "cmd": [
      "git",
      "checkout",
      "-f",
      "3d861fdb826c2f5cf270dd5f585d0e6057e1bf4f"
    ],
    "cwd": "[START_DIR]/binutils-gdb",
    "infra_step": true,
    "name": "git checkout"
  },
  {
    "cmd": [
      "git",
      "rev-parse",
      "HEAD"
    ],
    "cwd": "[START_DIR]/binutils-gdb",
    "infra_step": true,
    "name": "git rev-parse",
    "stdout": "/path/to/tmp/",
    "~followup_annotations": [
      "@@@SET_BUILD_PROPERTY@got_revision@\"deadbeef\"@@@"
    ]
  },
  {
    "cmd": [
      "git",
      "clean",
      "-f",
      "-d",
      "-x"
    ],
    "cwd": "[START_DIR]/binutils-gdb",
    "infra_step": true,
    "name": "git clean"
  },
  {
    "cmd": [
      "git",
      "submodule",
      "sync"
    ],
    "cwd": "[START_DIR]/binutils-gdb",
    "infra_step": true,
    "name": "submodule sync"
  },
  {
    "cmd": [
      "git",
      "submodule",
      "update",
      "--init"
    ],
    "cwd": "[START_DIR]/binutils-gdb",
    "infra_step": true,
    "name": "submodule update"
  },
  {
    "cmd": [
      "git",
      "diff",
      "--name-only",
      "5898623efb820fc56123da2e316756a9a32cb59b..3d861fdb826c2f5cf270dd5f585d0e6057e1bf4f"
    ],
    "cwd": "[START_DIR]/binutils-gdb",
    "infra_step": true,
    "name": "check for changes other than bfd/version.h",
    "stdout": "/path/to/tmp/",
    "~followup_annotations": [
      "@@@STEP_LOG_LINE@raw_io.output[changed files]@bfd/version.h@@@",
      "@@@STEP_LOG_END@raw_io.output[changed files]@@@"
    ]
  },
  {
    "cmd": [
      "python",
      "-u",
      "RECIPE_MODULE[recipe_engine::file]/resources/fileutil.py",
      "--json-output",
      "/path/to/tmp/json",
      "ensure-directory",
      "--mode",
      "0777",
      "[START_DIR]/gcc"
    ],
    "infra_step": true,
    "name": "makedirs (2)"
  },
  {
    "cmd": [
      "git",
      "init"
    ],
    "cwd": "[START_DIR]/gcc",
    "infra_step": true,
    "name": "git init (2)"
  },
  {
    "cmd": [
      "git",
      "remote",
      "add",
      "origin",
      "https://gnu.googlesource.com/gcc"
    ],
    "cwd": "[START_DIR]/gcc",
    "infra_step": true,
    "name": "git remote (2)"
  },
  {
    "cmd": [
      "git",
      "fetch",
      "origin"
    ],
    "cwd": "[START_DIR]/gcc",
    "infra_step": true,
    "name": "git fetch (2)"
  },
  {
    "cmd": [
      "git",
      "checkout",
      "-f",
      "4b5e15daff8b54440e3fda451c318ad31e532fab"
    ],
    "cwd": "[START_DIR]/gcc",
    "infra_step": true,
    "name": "git checkout (2)"
  },
  {
    "cmd": [
      "git",
      "rev-parse",
      "HEAD"
    ],
    "cwd": "[START_DIR]/gcc",
    "infra_step": true,
    "name": "git rev-parse (2)",
    "stdout": "/path/to/tmp/",
    "~followup_annotations": [
      "@@@SET_BUILD_PROPERTY@got_revision@\"deadbeef\"@@@"
    ]
  },
  {
    "cmd": [
      "git",
      "clean",
      "-f",
      "-d",
      "-x"
    ],
    "cwd": "[START_DIR]/gcc",
    "infra_step": true,
    "name": "git clean (2)"
  },
  {
    "cmd": [
      "git",
      "submodule",
      "sync"
    ],
    "cwd": "[START_DIR]/gcc",
    "infra_step": true,
    "name": "submodule sync (2)"
  },
  {
    "cmd": [
      "git",
      "submodule",
      "update",
      "--init"
    ],
    "cwd": "[START_DIR]/gcc",
    "infra_step": true,
    "name": "submodule update (2)"
  },
  {
    "cmd": [
      "git",
      "diff",
      "--name-only",
      "b824b5a2484202f6eabbe118b1cf7682ce77b76e..4b5e15daff8b54440e3fda451c318ad31e532fab"
    ],
    "cwd": "[START_DIR]/gcc",
    "infra_step": true,
    "name": "check for changes other than gcc/DATESTAMP",
    "stdout": "/path/to/tmp/",
    "~followup_annotations": [
      "@@@STEP_LOG_LINE@raw_io.output[changed files]@gcc/DATESTAMP@@@",
      "@@@STEP_LOG_END@raw_io.output[changed files]@@@"
    ]
  },
  {
    "cmd": [],
    "infra_step": true,
    "name": "Revisions contain no useful changes"
  },
  {
    "jsonResult": null,
    "name": "$result"
  }
]